data_management_demo/__init__.py
data_management_demo/main.py
data_management_demo/packages/AbstractPackages.py
data_management_demo/packages/LightsheetPackages.py
data_management_demo/packages/PackageExceptions.py
data_management_demo/packages/PackageFactory.py
data_management_demo/packages/__init__.py
data_management_demo/ui/ConsoleUI.py
data_management_demo/ui/__init__.py
data_management_demo/utilities/__init__.py
data_management_demo/utilities/zStackUtils.py
data_management_demo-0.0.1.dist-info/LICENSE
data_management_demo-0.0.1.dist-info/METADATA
data_management_demo-0.0.1.dist-info/WHEEL
data_management_demo-0.0.1.dist-info/top_level.txt
data_management_demo-0.0.1.dist-info/RECORD
